[
    {
        "name": "Point-Control",
        "category": "Fullstack",
        "headerImg": "/assets/image/point-control.png",
        "description": "This project is a backend API built with NestJS that allows users to “clock in” and have a history of hours worked, it also has UX/UI modeling and a frontend to provide a better experience.",
        "seeMore": { 
            "url": "https://github.com/igorttosta/Point-Control", 
            "text": "Explore the hub..." 
        },
        "techs": [
            "Nest.js",
            "Swagger",
            "Jest",
            "Figma",
            "React.js",
            "MUI"   
        ],
        "headerLinks": {
            "link": { 
                "privateSource": false,
                "url": "https://github.com/igorttosta/Point-Control", 
                "icon": "BsGithub" 
            }
        }
    },
    {
        "name": "E-Commerce",
        "category": "Fullstack",
        "headerImg": "/assets/image/e-commerce.png",
        "description": "A website built with the aim of purchasing and selling products, also has a quick purchase tool through an excel file.",
        "techs": [
            "Node.js", 
            "HTML5", 
            "CSS3", 
            "Bootstrap", 
            "Javascript", 
            "Express.js"
        ],
        "headerLinks": {
            "link": { 
                "privateSource": true,
                "url": "https://github.com/igorttosta", 
                "icon": "SiPrivateinternetaccess" 
            }
        }
    },
    {
        "name": "CIEDS - Web Site",
        "category": "UI/UX Design",
        "headerImg": "/assets/image/cieds-website.png",
        "description": "a prototype remodeling the appearance and user flow of the website made for an NGO",
        "seeMore": { 
            "url": "https://www.figma.com/proto/1pggvQQQXUzc8G0b6xWnwL/CIEDS-Web", 
            "text": "Explore the prototype..." 
        },
        "techs": [
            "Figma"
        ],
        "headerLinks": {
            "link": { 
                "privateSource": false,
                "url": "https://www.figma.com/proto/1pggvQQQXUzc8G0b6xWnwL/CIEDS-Web", 
                "icon": "FaFigma" 
            }
        }
    }
]